mcp_server_zoomeye/__init__.py
mcp_server_zoomeye/__main__.py
mcp_server_zoomeye/prompts.py
mcp_server_zoomeye/server.py
mcp_server_zoomeye-0.1.5.dist-info/METADATA
mcp_server_zoomeye-0.1.5.dist-info/WHEEL
mcp_server_zoomeye-0.1.5.dist-info/entry_points.txt
mcp_server_zoomeye-0.1.5.dist-info/RECORD
