Metadata-Version: 2.4
Name: mcp-server-zoomeye
Version: 0.1.5
Summary: A Model Context Protocol server providing tools for ZoomEye queries for LLMs
Author-email: zoomeye team <support@zoomeye.ai>
License: MIT
Keywords: llm,mcp,zoomeye
Classifier: Development Status :: 4 - Beta
Classifier: Intended Audience :: Developers
Classifier: License :: OSI Approved :: MIT License
Classifier: Programming Language :: Python :: 3
Classifier: Programming Language :: Python :: 3.10
Requires-Python: >=3.10
Requires-Dist: mcp>=1.0.0
Requires-Dist: pydantic>=2.0.0
Requires-Dist: python-dotenv>=1.0.0
Requires-Dist: requests>=2.32.3
